geezer/__init__.py
geezer/config.py
geezer/demo.py
geezer/log.py
geezer/version.py
geezer-0.1.3.dist-info/METADATA
geezer-0.1.3.dist-info/WHEEL
geezer-0.1.3.dist-info/top_level.txt
geezer-0.1.3.dist-info/RECORD
