Metadata-Version: 2.4
Name: geezer
Version: 0.1.3
Summary: Old-school debug logging for stylish devs
Home-page: https://github.com/FullBoreStudios/geezer
Author: Ben McNelly
Author-email: ben+geezer@fbstudios.com
Project-URL: Source, https://github.com/FullBoreStudios/geezer
Project-URL: Tracker, https://github.com/FullBoreStudios/geezer/issues
Project-URL: Documentation, https://github.com/FullBoreStudios/geezer#readme
Classifier: Programming Language :: Python :: 3
Classifier: License :: OSI Approved :: MIT License
Classifier: Operating System :: OS Independent
Requires-Python: >=3.6
Requires-Dist: rich
Dynamic: author
Dynamic: author-email
Dynamic: classifier
Dynamic: description
Dynamic: description-content-type
Dynamic: home-page
Dynamic: project-url
Dynamic: requires-dist
Dynamic: requires-python
Dynamic: summary
